colormap2d-0.2.0.dist-info/METADATA
colormap2d-0.2.0.dist-info/WHEEL
colormap2d-0.2.0.dist-info/licenses/LICENSE
colormap2d/__init__.py
colormap2d/cm.py
colormap2d/data/__init__.py
colormap2d/data/cyclic_pinwheel.npy
colormap2d/data/pinwheel.npy
colormap2d-0.2.0.dist-info/RECORD
