Metadata-Version: 2.1
Name: colormap2d
Version: 0.2.0
Summary: Colormap for 2D vectors
Author-Email: Matthieu Thiboust <14574229+mthiboust@users.noreply.github.com>
License: Licence Apache 2.0
Project-URL: Homepage, https://github.com/mthiboust/colormap2d
Requires-Python: >=3.9
Requires-Dist: numpy>=1.22
Requires-Dist: ruff>=0.1.2; extra == "dev"
Requires-Dist: ipykernel>=6.26.0; extra == "dev"
Requires-Dist: matplotlib>=3.8.0; extra == "dev"
Requires-Dist: pytest>=7.4.3; extra == "dev"
Provides-Extra: dev
